target_starrocks/__init__.py
target_starrocks/__main__.py
target_starrocks/sinks.py
target_starrocks/target.py
target_starrocks-0.0.1a5.dist-info/METADATA
target_starrocks-0.0.1a5.dist-info/WHEEL
target_starrocks-0.0.1a5.dist-info/entry_points.txt
target_starrocks-0.0.1a5.dist-info/licenses/LICENSE
target_starrocks-0.0.1a5.dist-info/RECORD
