Metadata-Version: 2.4
Name: target-starrocks
Version: 0.0.1a5
Summary: Singer target for StarRocks, built with the Meltano Singer SDK.
Author-email: Edgar Ramírez-Mondragón <edgarrm358@gmail.com>
License-Expression: Apache-2.0
License-File: LICENSE
Keywords: ELT,Meltano,StarRocks,singer-tap
Classifier: Intended Audience :: Developers
Classifier: Operating System :: OS Independent
Classifier: Programming Language :: Python :: 3.13
Classifier: Programming Language :: Python :: 3.14
Requires-Python: >=3.13
Requires-Dist: singer-sdk[faker]~=0.51.0
Requires-Dist: starrocks~=1.2.0
Provides-Extra: s3
Requires-Dist: s3fs~=2025.9.0; extra == 's3'
